{
  "config": {
    "brick_spawn_randomize": 10,
    "input_lead_ticks": 1,
    "max_players": 4,
    "powers_enabled": true,
    "powerups_per_round": 4,
    "protocol_version": 9,
    "snapshot_interval_ticks": 1,
    "tick_rate": 60
  },
  "input_stream": {
    "already_processed_input_entries_received": 812349,
    "already_processed_input_entries_received_buffered": 803395,
    "already_processed_input_entries_received_direct": 8954,
    "input_entries_rejected_too_far_ahead": 0,
    "input_packets_arrived_fully_stale": 8954,
    "input_packets_received": 54138
  },
  "key_messages": {
    "correction_sent": 65001,
    "gameplay_event_sent": 259,
    "input_recv": 54138,
    "snapshot_sent": 65001
  },
  "packets": {
    "bytes_recv": 1299768,
    "bytes_sent": 8988114,
    "malformed_recv": 0,
    "recv_attempts": 54201,
    "recv_failed": 1,
    "sent_attempts": 130511,
    "sent_failed": 0
  },
  "per_player_input_continuity": [
    {
      "buffered_deadline_recoveries": 0,
      "direct_deadline_consumes": 20419,
      "gaps": 1783,
      "last_processed_seq": 4574,
      "last_recv_seq": 4575,
      "pending_inputs": 1,
      "player_id": 0,
      "ts_ms": 32334414
    },
    {
      "buffered_deadline_recoveries": 1824,
      "direct_deadline_consumes": 15603,
      "gaps": 3883,
      "last_processed_seq": 3570,
      "last_recv_seq": 3575,
      "pending_inputs": 5,
      "player_id": 1,
      "ts_ms": 32334414
    },
    {
      "buffered_deadline_recoveries": 119,
      "direct_deadline_consumes": 9118,
      "gaps": 5538,
      "last_processed_seq": 4564,
      "last_recv_seq": 4575,
      "pending_inputs": 11,
      "player_id": 2,
      "ts_ms": 32334414
    }
  ],
  "recent_events": [
    {
      "channel_id": null,
      "detail_a": 0,
      "detail_b": 41379,
      "lifecycle_type": 0,
      "msg_type": null,
      "note": "",
      "packet_direction": 0,
      "packet_result": 0,
      "player_id": 0,
      "seq": 2365,
      "simulation_type": 0,
      "ts_ms": 32242930,
      "type": 6
    },
    {
      "channel_id": null,
      "detail_a": 5,
      "detail_b": 41385,
      "lifecycle_type": 0,
      "msg_type": null,
      "note": "server flow: end_of_match",
      "packet_direction": 0,
      "packet_result": 0,
      "player_id": null,
      "seq": 0,
      "simulation_type": 0,
      "ts_ms": 32243030,
      "type": 7
    },
    {
      "channel_id": null,
      "detail_a": 0,
      "detail_b": 41385,
      "lifecycle_type": 0,
      "msg_type": null,
      "note": "",
      "packet_direction": 0,
      "packet_result": 0,
      "player_id": 1,
      "seq": 0,
      "simulation_type": 2,
      "ts_ms": 32243030,
      "type": 6
    },
    {
      "channel_id": null,
      "detail_a": 0,
      "detail_b": 41565,
      "lifecycle_type": 0,
      "msg_type": null,
      "note": "server flow: lobby",
      "packet_direction": 0,
      "packet_result": 0,
      "player_id": null,
      "seq": 0,
      "simulation_type": 0,
      "ts_ms": 32246030,
      "type": 7
    },
    {
      "channel_id": null,
      "detail_a": 2,
      "detail_b": 0,
      "lifecycle_type": 0,
      "msg_type": null,
      "note": "",
      "packet_direction": 0,
      "packet_result": 0,
      "player_id": null,
      "seq": 0,
      "simulation_type": 0,
      "ts_ms": 32246911,
      "type": 3
    },
    {
      "channel_id": null,
      "detail_a": 2,
      "detail_b": 0,
      "lifecycle_type": 1,
      "msg_type": null,
      "note": "",
      "packet_direction": 0,
      "packet_result": 0,
      "player_id": 2,
      "seq": 0,
      "simulation_type": 0,
      "ts_ms": 32246911,
      "type": 3
    },
    {
      "channel_id": null,
      "detail_a": 6,
      "detail_b": 42054,
      "lifecycle_type": 0,
      "msg_type": null,
      "note": "server flow: in_match",
      "packet_direction": 0,
      "packet_result": 0,
      "player_id": null,
      "seq": 0,
      "simulation_type": 0,
      "ts_ms": 32254191,
      "type": 7
    },
    {
      "channel_id": null,
      "detail_a": 0,
      "detail_b": 42119,
      "lifecycle_type": 0,
      "msg_type": null,
      "note": "",
      "packet_direction": 0,
      "packet_result": 0,
      "player_id": 1,
      "seq": 1,
      "simulation_type": 1,
      "ts_ms": 32255263,
      "type": 6
    },
    {
      "channel_id": null,
      "detail_a": 0,
      "detail_b": 42121,
      "lifecycle_type": 0,
      "msg_type": null,
      "note": "",
      "packet_direction": 0,
      "packet_result": 0,
      "player_id": 0,
      "seq": 6,
      "simulation_type": 0,
      "ts_ms": 32255296,
      "type": 6
    },
    {
      "channel_id": null,
      "detail_a": 0,
      "detail_b": 42129,
      "lifecycle_type": 0,
      "msg_type": null,
      "note": "",
      "packet_direction": 0,
      "packet_result": 0,
      "player_id": 2,
      "seq": 4,
      "simulation_type": 0,
      "ts_ms": 32255430,
      "type": 6
    },
    {
      "channel_id": null,
      "detail_a": 0,
      "detail_b": 42136,
      "lifecycle_type": 0,
      "msg_type": null,
      "note": "",
      "packet_direction": 0,
      "packet_result": 0,
      "player_id": 1,
      "seq": 18,
      "simulation_type": 0,
      "ts_ms": 32255547,
      "type": 6
    },
    {
      "channel_id": null,
      "detail_a": 0,
      "detail_b": 42185,
      "lifecycle_type": 0,
      "msg_type": null,
      "note": "",
      "packet_direction": 0,
      "packet_result": 0,
      "player_id": 1,
      "seq": 67,
      "simulation_type": 1,
      "ts_ms": 32256363,
      "type": 6
    },
    {
      "channel_id": null,
      "detail_a": 0,
      "detail_b": 42186,
      "lifecycle_type": 0,
      "msg_type": null,
      "note": "",
      "packet_direction": 0,
      "packet_result": 0,
      "player_id": 0,
      "seq": 71,
      "simulation_type": 0,
      "ts_ms": 32256380,
      "type": 6
    },
    {
      "channel_id": null,
      "detail_a": 0,
      "detail_b": 42193,
      "lifecycle_type": 0,
      "msg_type": null,
      "note": "",
      "packet_direction": 0,
      "packet_result": 0,
      "player_id": 2,
      "seq": 68,
      "simulation_type": 0,
      "ts_ms": 32256496,
      "type": 6
    },
    {
      "channel_id": null,
      "detail_a": 0,
      "detail_b": 42198,
      "lifecycle_type": 0,
      "msg_type": null,
      "note": "",
      "packet_direction": 0,
      "packet_result": 0,
      "player_id": 1,
      "seq": 80,
      "simulation_type": 0,
      "ts_ms": 32256580,
      "type": 6
    },
    {
      "channel_id": null,
      "detail_a": 0,
      "detail_b": 42246,
      "lifecycle_type": 0,
      "msg_type": null,
      "note": "",
      "packet_direction": 0,
      "packet_result": 0,
      "player_id": 1,
      "seq": 128,
      "simulation_type": 1,
      "ts_ms": 32257380,
      "type": 6
    },
    {
      "channel_id": null,
      "detail_a": 0,
      "detail_b": 42253,
      "lifecycle_type": 0,
      "msg_type": null,
      "note": "",
      "packet_direction": 0,
      "packet_result": 0,
      "player_id": 2,
      "seq": 128,
      "simulation_type": 0,
      "ts_ms": 32257496,
      "type": 6
    },
    {
      "channel_id": null,
      "detail_a": 0,
      "detail_b": 42262,
      "lifecycle_type": 0,
      "msg_type": null,
      "note": "",
      "packet_direction": 0,
      "packet_result": 0,
      "player_id": 1,
      "seq": 144,
      "simulation_type": 0,
      "ts_ms": 32257646,
      "type": 6
    },
    {
      "channel_id": null,
      "detail_a": 0,
      "detail_b": 42265,
      "lifecycle_type": 0,
      "msg_type": null,
      "note": "",
      "packet_direction": 0,
      "packet_result": 0,
      "player_id": 0,
      "seq": 150,
      "simulation_type": 0,
      "ts_ms": 32257696,
      "type": 6
    },
    {
      "channel_id": null,
      "detail_a": 0,
      "detail_b": 42306,
      "lifecycle_type": 0,
      "msg_type": null,
      "note": "",
      "packet_direction": 0,
      "packet_result": 0,
      "player_id": 1,
      "seq": 188,
      "simulation_type": 1,
      "ts_ms": 32258380,
      "type": 6
    },
    {
      "channel_id": null,
      "detail_a": 8,
      "detail_b": 42313,
      "lifecycle_type": 0,
      "msg_type": null,
      "note": "",
      "packet_direction": 0,
      "packet_result": 0,
      "player_id": 2,
      "seq": 188,
      "simulation_type": 0,
      "ts_ms": 32258496,
      "type": 6
    },
    {
      "channel_id": null,
      "detail_a": 0,
      "detail_b": 42323,
      "lifecycle_type": 0,
      "msg_type": null,
      "note": "",
      "packet_direction": 0,
      "packet_result": 0,
      "player_id": 1,
      "seq": 205,
      "simulation_type": 0,
      "ts_ms": 32258663,
      "type": 6
    },
    {
      "channel_id": null,
      "detail_a": 0,
      "detail_b": 42330,
      "lifecycle_type": 0,
      "msg_type": null,
      "note": "",
      "packet_direction": 0,
      "packet_result": 0,
      "player_id": 0,
      "seq": 215,
      "simulation_type": 0,
      "ts_ms": 32258779,
      "type": 6
    },
    {
      "channel_id": null,
      "detail_a": 0,
      "detail_b": 42373,
      "lifecycle_type": 0,
      "msg_type": null,
      "note": "",
      "packet_direction": 0,
      "packet_result": 0,
      "player_id": 2,
      "seq": 248,
      "simulation_type": 0,
      "ts_ms": 32259497,
      "type": 6
    },
    {
      "channel_id": null,
      "detail_a": 0,
      "detail_b": 42385,
      "lifecycle_type": 0,
      "msg_type": null,
      "note": "",
      "packet_direction": 0,
      "packet_result": 0,
      "player_id": 1,
      "seq": 267,
      "simulation_type": 0,
      "ts_ms": 32259697,
      "type": 6
    },
    {
      "channel_id": null,
      "detail_a": 0,
      "detail_b": 42390,
      "lifecycle_type": 0,
      "msg_type": null,
      "note": "",
      "packet_direction": 0,
      "packet_result": 0,
      "player_id": 1,
      "seq": 272,
      "simulation_type": 1,
      "ts_ms": 32259780,
      "type": 6
    },
    {
      "channel_id": null,
      "detail_a": 0,
      "detail_b": 42391,
      "lifecycle_type": 0,
      "msg_type": null,
      "note": "",
      "packet_direction": 0,
      "packet_result": 0,
      "player_id": 0,
      "seq": 276,
      "simulation_type": 0,
      "ts_ms": 32259796,
      "type": 6
    },
    {
      "channel_id": null,
      "detail_a": 0,
      "detail_b": 42436,
      "lifecycle_type": 0,
      "msg_type": null,
      "note": "",
      "packet_direction": 0,
      "packet_result": 0,
      "player_id": 2,
      "seq": 311,
      "simulation_type": 0,
      "ts_ms": 32260547,
      "type": 6
    },
    {
      "channel_id": null,
      "detail_a": 0,
      "detail_b": 42448,
      "lifecycle_type": 0,
      "msg_type": null,
      "note": "",
      "packet_direction": 0,
      "packet_result": 0,
      "player_id": 1,
      "seq": 330,
      "simulation_type": 0,
      "ts_ms": 32260747,
      "type": 6
    },
    {
      "channel_id": null,
      "detail_a": 0,
      "detail_b": 42450,
      "lifecycle_type": 0,
      "msg_type": null,
      "note": "",
      "packet_direction": 0,
      "packet_result": 0,
      "player_id": 1,
      "seq": 332,
      "simulation_type": 1,
      "ts_ms": 32260780,
      "type": 6
    },
    {
      "channel_id": null,
      "detail_a": 0,
      "detail_b": 42465,
      "lifecycle_type": 0,
      "msg_type": null,
      "note": "",
      "packet_direction": 0,
      "packet_result": 0,
      "player_id": 0,
      "seq": 350,
      "simulation_type": 0,
      "ts_ms": 32261029,
      "type": 6
    },
    {
      "channel_id": null,
      "detail_a": 0,
      "detail_b": 42511,
      "lifecycle_type": 0,
      "msg_type": null,
      "note": "",
      "packet_direction": 0,
      "packet_result": 0,
      "player_id": 1,
      "seq": 393,
      "simulation_type": 0,
      "ts_ms": 32261797,
      "type": 6
    },
    {
      "channel_id": null,
      "detail_a": 4,
      "detail_b": 42512,
      "lifecycle_type": 0,
      "msg_type": null,
      "note": "",
      "packet_direction": 0,
      "packet_result": 0,
      "player_id": 2,
      "seq": 387,
      "simulation_type": 0,
      "ts_ms": 32261813,
      "type": 6
    },
    {
      "channel_id": null,
      "detail_a": 0,
      "detail_b": 42525,
      "lifecycle_type": 0,
      "msg_type": null,
      "note": "",
      "packet_direction": 0,
      "packet_result": 0,
      "player_id": 1,
      "seq": 407,
      "simulation_type": 1,
      "ts_ms": 32262029,
      "type": 6
    },
    {
      "channel_id": null,
      "detail_a": 0,
      "detail_b": 42541,
      "lifecycle_type": 0,
      "msg_type": null,
      "note": "",
      "packet_direction": 0,
      "packet_result": 0,
      "player_id": 0,
      "seq": 426,
      "simulation_type": 0,
      "ts_ms": 32262296,
      "type": 6
    },
    {
      "channel_id": null,
      "detail_a": 0,
      "detail_b": 42571,
      "lifecycle_type": 0,
      "msg_type": null,
      "note": "",
      "packet_direction": 0,
      "packet_result": 0,
      "player_id": 1,
      "seq": 453,
      "simulation_type": 0,
      "ts_ms": 32262797,
      "type": 6
    },
    {
      "channel_id": null,
      "detail_a": 8,
      "detail_b": 42572,
      "lifecycle_type": 0,
      "msg_type": null,
      "note": "",
      "packet_direction": 0,
      "packet_result": 0,
      "player_id": 2,
      "seq": 447,
      "simulation_type": 0,
      "ts_ms": 32262813,
      "type": 6
    },
    {
      "channel_id": null,
      "detail_a": 0,
      "detail_b": 42585,
      "lifecycle_type": 0,
      "msg_type": null,
      "note": "",
      "packet_direction": 0,
      "packet_result": 0,
      "player_id": 1,
      "seq": 467,
      "simulation_type": 1,
      "ts_ms": 32263029,
      "type": 6
    },
    {
      "channel_id": null,
      "detail_a": 0,
      "detail_b": 42627,
      "lifecycle_type": 0,
      "msg_type": null,
      "note": "",
      "packet_direction": 0,
      "packet_result": 0,
      "player_id": 0,
      "seq": 512,
      "simulation_type": 0,
      "ts_ms": 32263730,
      "type": 6
    },
    {
      "channel_id": null,
      "detail_a": 0,
      "detail_b": 42633,
      "lifecycle_type": 0,
      "msg_type": null,
      "note": "",
      "packet_direction": 0,
      "packet_result": 0,
      "player_id": 1,
      "seq": 515,
      "simulation_type": 0,
      "ts_ms": 32263829,
      "type": 6
    },
    {
      "channel_id": null,
      "detail_a": 0,
      "detail_b": 42634,
      "lifecycle_type": 0,
      "msg_type": null,
      "note": "",
      "packet_direction": 0,
      "packet_result": 0,
      "player_id": 2,
      "seq": 509,
      "simulation_type": 0,
      "ts_ms": 32263846,
      "type": 6
    },
    {
      "channel_id": null,
      "detail_a": 0,
      "detail_b": 42652,
      "lifecycle_type": 0,
      "msg_type": null,
      "note": "",
      "packet_direction": 0,
      "packet_result": 0,
      "player_id": 1,
      "seq": 534,
      "simulation_type": 1,
      "ts_ms": 32264145,
      "type": 6
    },
    {
      "channel_id": null,
      "detail_a": 0,
      "detail_b": 42696,
      "lifecycle_type": 0,
      "msg_type": null,
      "note": "",
      "packet_direction": 0,
      "packet_result": 0,
      "player_id": 2,
      "seq": 571,
      "simulation_type": 0,
      "ts_ms": 32264880,
      "type": 6
    },
    {
      "channel_id": null,
      "detail_a": 0,
      "detail_b": 42697,
      "lifecycle_type": 0,
      "msg_type": null,
      "note": "",
      "packet_direction": 0,
      "packet_result": 0,
      "player_id": 1,
      "seq": 579,
      "simulation_type": 0,
      "ts_ms": 32264896,
      "type": 6
    },
    {
      "channel_id": null,
      "detail_a": 0,
      "detail_b": 42699,
      "lifecycle_type": 0,
      "msg_type": null,
      "note": "",
      "packet_direction": 0,
      "packet_result": 0,
      "player_id": 0,
      "seq": 584,
      "simulation_type": 0,
      "ts_ms": 32264930,
      "type": 6
    },
    {
      "channel_id": null,
      "detail_a": 0,
      "detail_b": 42718,
      "lifecycle_type": 0,
      "msg_type": null,
      "note": "",
      "packet_direction": 0,
      "packet_result": 0,
      "player_id": 1,
      "seq": 600,
      "simulation_type": 1,
      "ts_ms": 32265247,
      "type": 6
    },
    {
      "channel_id": null,
      "detail_a": 4,
      "detail_b": 42760,
      "lifecycle_type": 0,
      "msg_type": null,
      "note": "",
      "packet_direction": 0,
      "packet_result": 0,
      "player_id": 2,
      "seq": 635,
      "simulation_type": 0,
      "ts_ms": 32265946,
      "type": 6
    },
    {
      "channel_id": null,
      "detail_a": 0,
      "detail_b": 42761,
      "lifecycle_type": 0,
      "msg_type": null,
      "note": "",
      "packet_direction": 0,
      "packet_result": 0,
      "player_id": 0,
      "seq": 646,
      "simulation_type": 0,
      "ts_ms": 32265963,
      "type": 6
    },
    {
      "channel_id": null,
      "detail_a": 0,
      "detail_b": 42780,
      "lifecycle_type": 0,
      "msg_type": null,
      "note": "",
      "packet_direction": 0,
      "packet_result": 0,
      "player_id": 1,
      "seq": 662,
      "simulation_type": 0,
      "ts_ms": 32266280,
      "type": 6
    },
    {
      "channel_id": null,
      "detail_a": 0,
      "detail_b": 42785,
      "lifecycle_type": 0,
      "msg_type": null,
      "note": "",
      "packet_direction": 0,
      "packet_result": 0,
      "player_id": 1,
      "seq": 667,
      "simulation_type": 1,
      "ts_ms": 32266363,
      "type": 6
    },
    {
      "channel_id": null,
      "detail_a": 0,
      "detail_b": 42829,
      "lifecycle_type": 0,
      "msg_type": null,
      "note": "",
      "packet_direction": 0,
      "packet_result": 0,
      "player_id": 0,
      "seq": 714,
      "simulation_type": 0,
      "ts_ms": 32267096,
      "type": 6
    },
    {
      "channel_id": null,
      "detail_a": 8,
      "detail_b": 42832,
      "lifecycle_type": 0,
      "msg_type": null,
      "note": "",
      "packet_direction": 0,
      "packet_result": 0,
      "player_id": 2,
      "seq": 707,
      "simulation_type": 0,
      "ts_ms": 32267147,
      "type": 6
    },
    {
      "channel_id": null,
      "detail_a": 0,
      "detail_b": 42844,
      "lifecycle_type": 0,
      "msg_type": null,
      "note": "",
      "packet_direction": 0,
      "packet_result": 0,
      "player_id": 1,
      "seq": 726,
      "simulation_type": 0,
      "ts_ms": 32267346,
      "type": 6
    },
    {
      "channel_id": null,
      "detail_a": 0,
      "detail_b": 42871,
      "lifecycle_type": 0,
      "msg_type": null,
      "note": "",
      "packet_direction": 0,
      "packet_result": 0,
      "player_id": 1,
      "seq": 753,
      "simulation_type": 1,
      "ts_ms": 32267796,
      "type": 6
    },
    {
      "channel_id": null,
      "detail_a": 0,
      "detail_b": 42895,
      "lifecycle_type": 0,
      "msg_type": null,
      "note": "",
      "packet_direction": 0,
      "packet_result": 0,
      "player_id": 2,
      "seq": 770,
      "simulation_type": 0,
      "ts_ms": 32268196,
      "type": 6
    },
    {
      "channel_id": null,
      "detail_a": 0,
      "detail_b": 42910,
      "lifecycle_type": 0,
      "msg_type": null,
      "note": "",
      "packet_direction": 0,
      "packet_result": 0,
      "player_id": 0,
      "seq": 795,
      "simulation_type": 0,
      "ts_ms": 32268446,
      "type": 6
    },
    {
      "channel_id": null,
      "detail_a": 0,
      "detail_b": 42912,
      "lifecycle_type": 0,
      "msg_type": null,
      "note": "",
      "packet_direction": 0,
      "packet_result": 0,
      "player_id": 1,
      "seq": 794,
      "simulation_type": 0,
      "ts_ms": 32268480,
      "type": 6
    },
    {
      "channel_id": null,
      "detail_a": 0,
      "detail_b": 42943,
      "lifecycle_type": 0,
      "msg_type": null,
      "note": "",
      "packet_direction": 0,
      "packet_result": 0,
      "player_id": 1,
      "seq": 825,
      "simulation_type": 1,
      "ts_ms": 32268996,
      "type": 6
    },
    {
      "channel_id": null,
      "detail_a": 0,
      "detail_b": 42958,
      "lifecycle_type": 0,
      "msg_type": null,
      "note": "",
      "packet_direction": 0,
      "packet_result": 0,
      "player_id": 2,
      "seq": 833,
      "simulation_type": 0,
      "ts_ms": 32269247,
      "type": 6
    },
    {
      "channel_id": null,
      "detail_a": 0,
      "detail_b": 42977,
      "lifecycle_type": 0,
      "msg_type": null,
      "note": "",
      "packet_direction": 0,
      "packet_result": 0,
      "player_id": 1,
      "seq": 859,
      "simulation_type": 0,
      "ts_ms": 32269563,
      "type": 6
    },
    {
      "channel_id": null,
      "detail_a": 0,
      "detail_b": 42985,
      "lifecycle_type": 0,
      "msg_type": null,
      "note": "",
      "packet_direction": 0,
      "packet_result": 0,
      "player_id": 0,
      "seq": 870,
      "simulation_type": 0,
      "ts_ms": 32269696,
      "type": 6
    },
    {
      "channel_id": null,
      "detail_a": 0,
      "detail_b": 43003,
      "lifecycle_type": 0,
      "msg_type": null,
      "note": "",
      "packet_direction": 0,
      "packet_result": 0,
      "player_id": 1,
      "seq": 885,
      "simulation_type": 1,
      "ts_ms": 32269996,
      "type": 6
    },
    {
      "channel_id": null,
      "detail_a": 4,
      "detail_b": 43021,
      "lifecycle_type": 0,
      "msg_type": null,
      "note": "",
      "packet_direction": 0,
      "packet_result": 0,
      "player_id": 2,
      "seq": 896,
      "simulation_type": 0,
      "ts_ms": 32270297,
      "type": 6
    },
    {
      "channel_id": null,
      "detail_a": 0,
      "detail_b": 43041,
      "lifecycle_type": 0,
      "msg_type": null,
      "note": "",
      "packet_direction": 0,
      "packet_result": 0,
      "player_id": 1,
      "seq": 923,
      "simulation_type": 0,
      "ts_ms": 32270630,
      "type": 6
    },
    {
      "channel_id": null,
      "detail_a": 0,
      "detail_b": 43048,
      "lifecycle_type": 0,
      "msg_type": null,
      "note": "",
      "packet_direction": 0,
      "packet_result": 0,
      "player_id": 0,
      "seq": 933,
      "simulation_type": 0,
      "ts_ms": 32270746,
      "type": 6
    },
    {
      "channel_id": null,
      "detail_a": 0,
      "detail_b": 43082,
      "lifecycle_type": 0,
      "msg_type": null,
      "note": "",
      "packet_direction": 0,
      "packet_result": 0,
      "player_id": 1,
      "seq": 964,
      "simulation_type": 1,
      "ts_ms": 32271313,
      "type": 6
    },
    {
      "channel_id": null,
      "detail_a": 8,
      "detail_b": 43083,
      "lifecycle_type": 0,
      "msg_type": null,
      "note": "",
      "packet_direction": 0,
      "packet_result": 0,
      "player_id": 2,
      "seq": 958,
      "simulation_type": 0,
      "ts_ms": 32271329,
      "type": 6
    },
    {
      "channel_id": null,
      "detail_a": 0,
      "detail_b": 43102,
      "lifecycle_type": 0,
      "msg_type": null,
      "note": "",
      "packet_direction": 0,
      "packet_result": 0,
      "player_id": 1,
      "seq": 984,
      "simulation_type": 0,
      "ts_ms": 32271646,
      "type": 6
    },
    {
      "channel_id": null,
      "detail_a": 0,
      "detail_b": 43120,
      "lifecycle_type": 0,
      "msg_type": null,
      "note": "",
      "packet_direction": 0,
      "packet_result": 0,
      "player_id": 0,
      "seq": 1005,
      "simulation_type": 0,
      "ts_ms": 32271947,
      "type": 6
    },
    {
      "channel_id": null,
      "detail_a": 0,
      "detail_b": 43142,
      "lifecycle_type": 0,
      "msg_type": null,
      "note": "",
      "packet_direction": 0,
      "packet_result": 0,
      "player_id": 1,
      "seq": 1024,
      "simulation_type": 1,
      "ts_ms": 32272313,
      "type": 6
    },
    {
      "channel_id": null,
      "detail_a": 0,
      "detail_b": 43147,
      "lifecycle_type": 0,
      "msg_type": null,
      "note": "",
      "packet_direction": 0,
      "packet_result": 0,
      "player_id": 2,
      "seq": 1022,
      "simulation_type": 0,
      "ts_ms": 32272397,
      "type": 6
    },
    {
      "channel_id": null,
      "detail_a": 0,
      "detail_b": 43175,
      "lifecycle_type": 0,
      "msg_type": null,
      "note": "",
      "packet_direction": 0,
      "packet_result": 0,
      "player_id": 1,
      "seq": 1057,
      "simulation_type": 0,
      "ts_ms": 32272863,
      "type": 6
    },
    {
      "channel_id": null,
      "detail_a": 0,
      "detail_b": 43209,
      "lifecycle_type": 0,
      "msg_type": null,
      "note": "",
      "packet_direction": 0,
      "packet_result": 0,
      "player_id": 1,
      "seq": 1091,
      "simulation_type": 1,
      "ts_ms": 32273429,
      "type": 6
    },
    {
      "channel_id": null,
      "detail_a": 4,
      "detail_b": 43210,
      "lifecycle_type": 0,
      "msg_type": null,
      "note": "",
      "packet_direction": 0,
      "packet_result": 0,
      "player_id": 2,
      "seq": 1085,
      "simulation_type": 0,
      "ts_ms": 32273446,
      "type": 6
    },
    {
      "channel_id": null,
      "detail_a": 0,
      "detail_b": 43211,
      "lifecycle_type": 0,
      "msg_type": null,
      "note": "",
      "packet_direction": 0,
      "packet_result": 0,
      "player_id": 0,
      "seq": 1096,
      "simulation_type": 0,
      "ts_ms": 32273462,
      "type": 6
    },
    {
      "channel_id": null,
      "detail_a": 0,
      "detail_b": 43246,
      "lifecycle_type": 0,
      "msg_type": null,
      "note": "",
      "packet_direction": 0,
      "packet_result": 0,
      "player_id": 1,
      "seq": 1128,
      "simulation_type": 0,
      "ts_ms": 32274046,
      "type": 6
    },
    {
      "channel_id": null,
      "detail_a": 4,
      "detail_b": 43270,
      "lifecycle_type": 0,
      "msg_type": null,
      "note": "",
      "packet_direction": 0,
      "packet_result": 0,
      "player_id": 2,
      "seq": 1145,
      "simulation_type": 0,
      "ts_ms": 32274446,
      "type": 6
    },
    {
      "channel_id": null,
      "detail_a": 0,
      "detail_b": 43271,
      "lifecycle_type": 0,
      "msg_type": null,
      "note": "",
      "packet_direction": 0,
      "packet_result": 0,
      "player_id": 1,
      "seq": 1153,
      "simulation_type": 1,
      "ts_ms": 32274463,
      "type": 6
    },
    {
      "channel_id": null,
      "detail_a": 0,
      "detail_b": 43273,
      "lifecycle_type": 0,
      "msg_type": null,
      "note": "",
      "packet_direction": 0,
      "packet_result": 0,
      "player_id": 0,
      "seq": 1158,
      "simulation_type": 0,
      "ts_ms": 32274496,
      "type": 6
    },
    {
      "channel_id": null,
      "detail_a": 0,
      "detail_b": 43315,
      "lifecycle_type": 0,
      "msg_type": null,
      "note": "",
      "packet_direction": 0,
      "packet_result": 0,
      "player_id": 1,
      "seq": 1197,
      "simulation_type": 0,
      "ts_ms": 32275195,
      "type": 6
    },
    {
      "channel_id": null,
      "detail_a": 4,
      "detail_b": 43339,
      "lifecycle_type": 0,
      "msg_type": null,
      "note": "",
      "packet_direction": 0,
      "packet_result": 0,
      "player_id": 2,
      "seq": 1214,
      "simulation_type": 0,
      "ts_ms": 32275597,
      "type": 6
    },
    {
      "channel_id": null,
      "detail_a": 0,
      "detail_b": 43344,
      "lifecycle_type": 0,
      "msg_type": null,
      "note": "",
      "packet_direction": 0,
      "packet_result": 0,
      "player_id": 0,
      "seq": 1229,
      "simulation_type": 0,
      "ts_ms": 32275679,
      "type": 6
    },
    {
      "channel_id": null,
      "detail_a": 0,
      "detail_b": 43350,
      "lifecycle_type": 0,
      "msg_type": null,
      "note": "",
      "packet_direction": 0,
      "packet_result": 0,
      "player_id": 1,
      "seq": 1232,
      "simulation_type": 1,
      "ts_ms": 32275780,
      "type": 6
    },
    {
      "channel_id": null,
      "detail_a": 0,
      "detail_b": 43386,
      "lifecycle_type": 0,
      "msg_type": null,
      "note": "",
      "packet_direction": 0,
      "packet_result": 0,
      "player_id": 1,
      "seq": 1268,
      "simulation_type": 0,
      "ts_ms": 32276380,
      "type": 6
    },
    {
      "channel_id": null,
      "detail_a": 8,
      "detail_b": 43401,
      "lifecycle_type": 0,
      "msg_type": null,
      "note": "",
      "packet_direction": 0,
      "packet_result": 0,
      "player_id": 2,
      "seq": 1276,
      "simulation_type": 0,
      "ts_ms": 32276630,
      "type": 6
    },
    {
      "channel_id": null,
      "detail_a": 0,
      "detail_b": 43414,
      "lifecycle_type": 0,
      "msg_type": null,
      "note": "",
      "packet_direction": 0,
      "packet_result": 0,
      "player_id": 1,
      "seq": 1296,
      "simulation_type": 1,
      "ts_ms": 32276846,
      "type": 6
    },
    {
      "channel_id": null,
      "detail_a": 0,
      "detail_b": 43419,
      "lifecycle_type": 0,
      "msg_type": null,
      "note": "",
      "packet_direction": 0,
      "packet_result": 0,
      "player_id": 0,
      "seq": 1304,
      "simulation_type": 0,
      "ts_ms": 32276929,
      "type": 6
    },
    {
      "channel_id": null,
      "detail_a": 0,
      "detail_b": 43453,
      "lifecycle_type": 0,
      "msg_type": null,
      "note": "",
      "packet_direction": 0,
      "packet_result": 0,
      "player_id": 1,
      "seq": 1335,
      "simulation_type": 0,
      "ts_ms": 32277496,
      "type": 6
    },
    {
      "channel_id": null,
      "detail_a": 0,
      "detail_b": 43462,
      "lifecycle_type": 0,
      "msg_type": null,
      "note": "",
      "packet_direction": 0,
      "packet_result": 0,
      "player_id": 2,
      "seq": 1337,
      "simulation_type": 0,
      "ts_ms": 32277647,
      "type": 6
    },
    {
      "channel_id": null,
      "detail_a": 0,
      "detail_b": 43475,
      "lifecycle_type": 0,
      "msg_type": null,
      "note": "",
      "packet_direction": 0,
      "packet_result": 0,
      "player_id": 1,
      "seq": 1357,
      "simulation_type": 1,
      "ts_ms": 32277863,
      "type": 6
    },
    {
      "channel_id": null,
      "detail_a": 0,
      "detail_b": 43487,
      "lifecycle_type": 0,
      "msg_type": null,
      "note": "",
      "packet_direction": 0,
      "packet_result": 0,
      "player_id": 0,
      "seq": 1372,
      "simulation_type": 0,
      "ts_ms": 32278063,
      "type": 6
    },
    {
      "channel_id": null,
      "detail_a": 0,
      "detail_b": 43525,
      "lifecycle_type": 0,
      "msg_type": null,
      "note": "",
      "packet_direction": 0,
      "packet_result": 0,
      "player_id": 2,
      "seq": 1400,
      "simulation_type": 0,
      "ts_ms": 32278697,
      "type": 6
    },
    {
      "channel_id": null,
      "detail_a": 0,
      "detail_b": 43539,
      "lifecycle_type": 0,
      "msg_type": null,
      "note": "",
      "packet_direction": 0,
      "packet_result": 0,
      "player_id": 1,
      "seq": 1421,
      "simulation_type": 0,
      "ts_ms": 32278930,
      "type": 6
    },
    {
      "channel_id": null,
      "detail_a": 0,
      "detail_b": 43552,
      "lifecycle_type": 0,
      "msg_type": null,
      "note": "",
      "packet_direction": 0,
      "packet_result": 0,
      "player_id": 0,
      "seq": 1437,
      "simulation_type": 0,
      "ts_ms": 32279146,
      "type": 6
    },
    {
      "channel_id": null,
      "detail_a": 0,
      "detail_b": 43564,
      "lifecycle_type": 0,
      "msg_type": null,
      "note": "",
      "packet_direction": 0,
      "packet_result": 0,
      "player_id": 1,
      "seq": 1446,
      "simulation_type": 1,
      "ts_ms": 32279346,
      "type": 6
    },
    {
      "channel_id": null,
      "detail_a": 1,
      "detail_b": 43586,
      "lifecycle_type": 0,
      "msg_type": null,
      "note": "",
      "packet_direction": 0,
      "packet_result": 0,
      "player_id": 2,
      "seq": 1461,
      "simulation_type": 0,
      "ts_ms": 32279713,
      "type": 6
    },
    {
      "channel_id": null,
      "detail_a": 0,
      "detail_b": 43609,
      "lifecycle_type": 0,
      "msg_type": null,
      "note": "",
      "packet_direction": 0,
      "packet_result": 0,
      "player_id": 1,
      "seq": 1491,
      "simulation_type": 0,
      "ts_ms": 32280096,
      "type": 6
    },
    {
      "channel_id": null,
      "detail_a": 0,
      "detail_b": 43616,
      "lifecycle_type": 0,
      "msg_type": null,
      "note": "",
      "packet_direction": 0,
      "packet_result": 0,
      "player_id": 0,
      "seq": 1501,
      "simulation_type": 0,
      "ts_ms": 32280213,
      "type": 6
    },
    {
      "channel_id": null,
      "detail_a": 0,
      "detail_b": 43633,
      "lifecycle_type": 0,
      "msg_type": null,
      "note": "",
      "packet_direction": 0,
      "packet_result": 0,
      "player_id": 1,
      "seq": 1515,
      "simulation_type": 1,
      "ts_ms": 32280497,
      "type": 6
    },
    {
      "channel_id": null,
      "detail_a": 0,
      "detail_b": 43646,
      "lifecycle_type": 0,
      "msg_type": null,
      "note": "",
      "packet_direction": 0,
      "packet_result": 0,
      "player_id": 2,
      "seq": 1521,
      "simulation_type": 0,
      "ts_ms": 32280713,
      "type": 6
    },
    {
      "channel_id": null,
      "detail_a": 0,
      "detail_b": 43672,
      "lifecycle_type": 0,
      "msg_type": null,
      "note": "",
      "packet_direction": 0,
      "packet_result": 0,
      "player_id": 1,
      "seq": 1554,
      "simulation_type": 0,
      "ts_ms": 32281146,
      "type": 6
    },
    {
      "channel_id": null,
      "detail_a": 2,
      "detail_b": 43706,
      "lifecycle_type": 0,
      "msg_type": null,
      "note": "",
      "packet_direction": 0,
      "packet_result": 0,
      "player_id": 2,
      "seq": 1581,
      "simulation_type": 0,
      "ts_ms": 32281713,
      "type": 6
    },
    {
      "channel_id": null,
      "detail_a": 0,
      "detail_b": 43707,
      "lifecycle_type": 0,
      "msg_type": null,
      "note": "",
      "packet_direction": 0,
      "packet_result": 0,
      "player_id": 1,
      "seq": 1589,
      "simulation_type": 1,
      "ts_ms": 32281730,
      "type": 6
    },
    {
      "channel_id": null,
      "detail_a": 0,
      "detail_b": 43720,
      "lifecycle_type": 0,
      "msg_type": null,
      "note": "",
      "packet_direction": 0,
      "packet_result": 0,
      "player_id": 0,
      "seq": 1605,
      "simulation_type": 0,
      "ts_ms": 32281946,
      "type": 6
    },
    {
      "channel_id": null,
      "detail_a": 0,
      "detail_b": 43732,
      "lifecycle_type": 0,
      "msg_type": null,
      "note": "",
      "packet_direction": 0,
      "packet_result": 0,
      "player_id": 1,
      "seq": 1614,
      "simulation_type": 0,
      "ts_ms": 32282146,
      "type": 6
    },
    {
      "channel_id": null,
      "detail_a": 4,
      "detail_b": 43771,
      "lifecycle_type": 0,
      "msg_type": null,
      "note": "",
      "packet_direction": 0,
      "packet_result": 0,
      "player_id": 2,
      "seq": 1646,
      "simulation_type": 0,
      "ts_ms": 32282797,
      "type": 6
    },
    {
      "channel_id": null,
      "detail_a": 0,
      "detail_b": 43781,
      "lifecycle_type": 0,
      "msg_type": null,
      "note": "",
      "packet_direction": 0,
      "packet_result": 0,
      "player_id": 1,
      "seq": 1663,
      "simulation_type": 1,
      "ts_ms": 32282963,
      "type": 6
    },
    {
      "channel_id": null,
      "detail_a": 0,
      "detail_b": 43795,
      "lifecycle_type": 0,
      "msg_type": null,
      "note": "",
      "packet_direction": 0,
      "packet_result": 0,
      "player_id": 0,
      "seq": 1680,
      "simulation_type": 0,
      "ts_ms": 32283196,
      "type": 6
    },
    {
      "channel_id": null,
      "detail_a": 0,
      "detail_b": 43798,
      "lifecycle_type": 0,
      "msg_type": null,
      "note": "",
      "packet_direction": 0,
      "packet_result": 0,
      "player_id": 1,
      "seq": 1680,
      "simulation_type": 0,
      "ts_ms": 32283246,
      "type": 6
    },
    {
      "channel_id": null,
      "detail_a": 8,
      "detail_b": 43836,
      "lifecycle_type": 0,
      "msg_type": null,
      "note": "",
      "packet_direction": 0,
      "packet_result": 0,
      "player_id": 2,
      "seq": 1711,
      "simulation_type": 0,
      "ts_ms": 32283880,
      "type": 6
    },
    {
      "channel_id": null,
      "detail_a": 0,
      "detail_b": 43854,
      "lifecycle_type": 0,
      "msg_type": null,
      "note": "",
      "packet_direction": 0,
      "packet_result": 0,
      "player_id": 1,
      "seq": 1736,
      "simulation_type": 1,
      "ts_ms": 32284179,
      "type": 6
    },
    {
      "channel_id": null,
      "detail_a": 0,
      "detail_b": 43857,
      "lifecycle_type": 0,
      "msg_type": null,
      "note": "",
      "packet_direction": 0,
      "packet_result": 0,
      "player_id": 0,
      "seq": 1742,
      "simulation_type": 0,
      "ts_ms": 32284229,
      "type": 6
    },
    {
      "channel_id": null,
      "detail_a": 0,
      "detail_b": 43880,
      "lifecycle_type": 0,
      "msg_type": null,
      "note": "",
      "packet_direction": 0,
      "packet_result": 0,
      "player_id": 1,
      "seq": 1762,
      "simulation_type": 0,
      "ts_ms": 32284613,
      "type": 6
    },
    {
      "channel_id": null,
      "detail_a": 0,
      "detail_b": 43899,
      "lifecycle_type": 0,
      "msg_type": null,
      "note": "",
      "packet_direction": 0,
      "packet_result": 0,
      "player_id": 2,
      "seq": 1774,
      "simulation_type": 0,
      "ts_ms": 32284930,
      "type": 6
    },
    {
      "channel_id": null,
      "detail_a": 0,
      "detail_b": 43916,
      "lifecycle_type": 0,
      "msg_type": null,
      "note": "",
      "packet_direction": 0,
      "packet_result": 0,
      "player_id": 1,
      "seq": 1798,
      "simulation_type": 1,
      "ts_ms": 32285213,
      "type": 6
    },
    {
      "channel_id": null,
      "detail_a": 0,
      "detail_b": 43918,
      "lifecycle_type": 0,
      "msg_type": null,
      "note": "",
      "packet_direction": 0,
      "packet_result": 0,
      "player_id": 0,
      "seq": 1803,
      "simulation_type": 0,
      "ts_ms": 32285246,
      "type": 6
    },
    {
      "channel_id": null,
      "detail_a": 0,
      "detail_b": 43940,
      "lifecycle_type": 0,
      "msg_type": null,
      "note": "",
      "packet_direction": 0,
      "packet_result": 0,
      "player_id": 1,
      "seq": 1822,
      "simulation_type": 0,
      "ts_ms": 32285613,
      "type": 6
    },
    {
      "channel_id": null,
      "detail_a": 2,
      "detail_b": 43960,
      "lifecycle_type": 0,
      "msg_type": null,
      "note": "",
      "packet_direction": 0,
      "packet_result": 0,
      "player_id": 2,
      "seq": 1835,
      "simulation_type": 0,
      "ts_ms": 32285946,
      "type": 6
    },
    {
      "channel_id": null,
      "detail_a": 0,
      "detail_b": 43987,
      "lifecycle_type": 0,
      "msg_type": null,
      "note": "",
      "packet_direction": 0,
      "packet_result": 0,
      "player_id": 1,
      "seq": 1869,
      "simulation_type": 1,
      "ts_ms": 32286396,
      "type": 6
    },
    {
      "channel_id": null,
      "detail_a": 0,
      "detail_b": 44002,
      "lifecycle_type": 0,
      "msg_type": null,
      "note": "",
      "packet_direction": 0,
      "packet_result": 0,
      "player_id": 0,
      "seq": 1887,
      "simulation_type": 0,
      "ts_ms": 32286647,
      "type": 6
    },
    {
      "channel_id": null,
      "detail_a": 0,
      "detail_b": 44008,
      "lifecycle_type": 0,
      "msg_type": null,
      "note": "",
      "packet_direction": 0,
      "packet_result": 0,
      "player_id": 1,
      "seq": 1890,
      "simulation_type": 0,
      "ts_ms": 32286747,
      "type": 6
    },
    {
      "channel_id": null,
      "detail_a": 0,
      "detail_b": 44024,
      "lifecycle_type": 0,
      "msg_type": null,
      "note": "",
      "packet_direction": 0,
      "packet_result": 0,
      "player_id": 2,
      "seq": 1899,
      "simulation_type": 0,
      "ts_ms": 32287013,
      "type": 6
    },
    {
      "channel_id": null,
      "detail_a": 0,
      "detail_b": 44058,
      "lifecycle_type": 0,
      "msg_type": null,
      "note": "",
      "packet_direction": 0,
      "packet_result": 0,
      "player_id": 1,
      "seq": 1940,
      "simulation_type": 1,
      "ts_ms": 32287580,
      "type": 6
    },
    {
      "channel_id": null,
      "detail_a": 0,
      "detail_b": 44073,
      "lifecycle_type": 0,
      "msg_type": null,
      "note": "",
      "packet_direction": 0,
      "packet_result": 0,
      "player_id": 1,
      "seq": 1955,
      "simulation_type": 0,
      "ts_ms": 32287830,
      "type": 6
    },
    {
      "channel_id": null,
      "detail_a": 1,
      "detail_b": 44084,
      "lifecycle_type": 0,
      "msg_type": null,
      "note": "",
      "packet_direction": 0,
      "packet_result": 0,
      "player_id": 2,
      "seq": 1959,
      "simulation_type": 0,
      "ts_ms": 32288013,
      "type": 6
    },
    {
      "channel_id": null,
      "detail_a": 0,
      "detail_b": 44094,
      "lifecycle_type": 0,
      "msg_type": null,
      "note": "",
      "packet_direction": 0,
      "packet_result": 0,
      "player_id": 0,
      "seq": 1979,
      "simulation_type": 0,
      "ts_ms": 32288180,
      "type": 6
    },
    {
      "channel_id": null,
      "detail_a": 0,
      "detail_b": 44134,
      "lifecycle_type": 0,
      "msg_type": null,
      "note": "",
      "packet_direction": 0,
      "packet_result": 0,
      "player_id": 1,
      "seq": 2016,
      "simulation_type": 1,
      "ts_ms": 32288845,
      "type": 6
    },
    {
      "channel_id": null,
      "detail_a": 4,
      "detail_b": 44146,
      "lifecycle_type": 0,
      "msg_type": null,
      "note": "",
      "packet_direction": 0,
      "packet_result": 0,
      "player_id": 2,
      "seq": 2021,
      "simulation_type": 0,
      "ts_ms": 32289046,
      "type": 6
    },
    {
      "channel_id": null,
      "detail_a": 0,
      "detail_b": 44148,
      "lifecycle_type": 0,
      "msg_type": null,
      "note": "",
      "packet_direction": 0,
      "packet_result": 0,
      "player_id": 1,
      "seq": 2030,
      "simulation_type": 0,
      "ts_ms": 32289079,
      "type": 6
    },
    {
      "channel_id": null,
      "detail_a": 0,
      "detail_b": 44156,
      "lifecycle_type": 0,
      "msg_type": null,
      "note": "",
      "packet_direction": 0,
      "packet_result": 0,
      "player_id": 0,
      "seq": 2041,
      "simulation_type": 0,
      "ts_ms": 32289213,
      "type": 6
    },
    {
      "channel_id": null,
      "detail_a": 0,
      "detail_b": 44195,
      "lifecycle_type": 0,
      "msg_type": null,
      "note": "",
      "packet_direction": 0,
      "packet_result": 0,
      "player_id": 1,
      "seq": 2077,
      "simulation_type": 1,
      "ts_ms": 32289864,
      "type": 6
    },
    {
      "channel_id": null,
      "detail_a": 2,
      "detail_b": 44207,
      "lifecycle_type": 0,
      "msg_type": null,
      "note": "",
      "packet_direction": 0,
      "packet_result": 0,
      "player_id": 2,
      "seq": 2082,
      "simulation_type": 0,
      "ts_ms": 32290063,
      "type": 6
    },
    {
      "channel_id": null,
      "detail_a": 0,
      "detail_b": 44209,
      "lifecycle_type": 0,
      "msg_type": null,
      "note": "",
      "packet_direction": 0,
      "packet_result": 0,
      "player_id": 1,
      "seq": 2091,
      "simulation_type": 0,
      "ts_ms": 32290096,
      "type": 6
    },
    {
      "channel_id": null,
      "detail_a": 0,
      "detail_b": 44245,
      "lifecycle_type": 0,
      "msg_type": null,
      "note": "",
      "packet_direction": 0,
      "packet_result": 0,
      "player_id": 0,
      "seq": 2130,
      "simulation_type": 0,
      "ts_ms": 32290696,
      "type": 6
    },
    {
      "channel_id": null,
      "detail_a": 0,
      "detail_b": 44256,
      "lifecycle_type": 0,
      "msg_type": null,
      "note": "",
      "packet_direction": 0,
      "packet_result": 0,
      "player_id": 1,
      "seq": 2138,
      "simulation_type": 1,
      "ts_ms": 32290880,
      "type": 6
    },
    {
      "channel_id": null,
      "detail_a": 4,
      "detail_b": 44272,
      "lifecycle_type": 0,
      "msg_type": null,
      "note": "",
      "packet_direction": 0,
      "packet_result": 0,
      "player_id": 2,
      "seq": 2147,
      "simulation_type": 0,
      "ts_ms": 32291147,
      "type": 6
    },
    {
      "channel_id": null,
      "detail_a": 0,
      "detail_b": 44286,
      "lifecycle_type": 0,
      "msg_type": null,
      "note": "",
      "packet_direction": 0,
      "packet_result": 0,
      "player_id": 1,
      "seq": 2168,
      "simulation_type": 0,
      "ts_ms": 32291380,
      "type": 6
    },
    {
      "channel_id": null,
      "detail_a": 0,
      "detail_b": 44307,
      "lifecycle_type": 0,
      "msg_type": null,
      "note": "",
      "packet_direction": 0,
      "packet_result": 0,
      "player_id": 0,
      "seq": 2192,
      "simulation_type": 0,
      "ts_ms": 32291729,
      "type": 6
    },
    {
      "channel_id": null,
      "detail_a": 0,
      "detail_b": 44322,
      "lifecycle_type": 0,
      "msg_type": null,
      "note": "",
      "packet_direction": 0,
      "packet_result": 0,
      "player_id": 1,
      "seq": 2204,
      "simulation_type": 1,
      "ts_ms": 32291980,
      "type": 6
    },
    {
      "channel_id": null,
      "detail_a": 0,
      "detail_b": 44333,
      "lifecycle_type": 0,
      "msg_type": null,
      "note": "",
      "packet_direction": 0,
      "packet_result": 0,
      "player_id": 2,
      "seq": 2208,
      "simulation_type": 0,
      "ts_ms": 32292163,
      "type": 6
    },
    {
      "channel_id": null,
      "detail_a": 0,
      "detail_b": 44351,
      "lifecycle_type": 0,
      "msg_type": null,
      "note": "",
      "packet_direction": 0,
      "packet_result": 0,
      "player_id": 1,
      "seq": 2233,
      "simulation_type": 0,
      "ts_ms": 32292464,
      "type": 6
    },
    {
      "channel_id": null,
      "detail_a": 0,
      "detail_b": 44383,
      "lifecycle_type": 0,
      "msg_type": null,
      "note": "",
      "packet_direction": 0,
      "packet_result": 0,
      "player_id": 1,
      "seq": 2265,
      "simulation_type": 1,
      "ts_ms": 32292997,
      "type": 6
    },
    {
      "channel_id": null,
      "detail_a": 0,
      "detail_b": 44393,
      "lifecycle_type": 0,
      "msg_type": null,
      "note": "",
      "packet_direction": 0,
      "packet_result": 0,
      "player_id": 2,
      "seq": 2268,
      "simulation_type": 0,
      "ts_ms": 32293163,
      "type": 6
    },
    {
      "channel_id": null,
      "detail_a": 0,
      "detail_b": 44395,
      "lifecycle_type": 0,
      "msg_type": null,
      "note": "",
      "packet_direction": 0,
      "packet_result": 0,
      "player_id": 0,
      "seq": 2280,
      "simulation_type": 0,
      "ts_ms": 32293196,
      "type": 6
    },
    {
      "channel_id": null,
      "detail_a": 0,
      "detail_b": 44440,
      "lifecycle_type": 0,
      "msg_type": null,
      "note": "",
      "packet_direction": 0,
      "packet_result": 0,
      "player_id": 1,
      "seq": 2322,
      "simulation_type": 0,
      "ts_ms": 32293947,
      "type": 6
    },
    {
      "channel_id": null,
      "detail_a": 0,
      "detail_b": 44445,
      "lifecycle_type": 0,
      "msg_type": null,
      "note": "",
      "packet_direction": 0,
      "packet_result": 0,
      "player_id": 1,
      "seq": 2327,
      "simulation_type": 1,
      "ts_ms": 32294030,
      "type": 6
    },
    {
      "channel_id": null,
      "detail_a": 8,
      "detail_b": 44453,
      "lifecycle_type": 0,
      "msg_type": null,
      "note": "",
      "packet_direction": 0,
      "packet_result": 0,
      "player_id": 2,
      "seq": 2328,
      "simulation_type": 0,
      "ts_ms": 32294164,
      "type": 6
    },
    {
      "channel_id": null,
      "detail_a": 0,
      "detail_b": 44459,
      "lifecycle_type": 0,
      "msg_type": null,
      "note": "",
      "packet_direction": 0,
      "packet_result": 0,
      "player_id": 0,
      "seq": 2344,
      "simulation_type": 0,
      "ts_ms": 32294263,
      "type": 6
    },
    {
      "channel_id": null,
      "detail_a": 0,
      "detail_b": 44508,
      "lifecycle_type": 0,
      "msg_type": null,
      "note": "",
      "packet_direction": 0,
      "packet_result": 0,
      "player_id": 1,
      "seq": 2390,
      "simulation_type": 0,
      "ts_ms": 32295079,
      "type": 6
    },
    {
      "channel_id": null,
      "detail_a": 0,
      "detail_b": 44511,
      "lifecycle_type": 0,
      "msg_type": null,
      "note": "",
      "packet_direction": 0,
      "packet_result": 0,
      "player_id": 1,
      "seq": 2393,
      "simulation_type": 1,
      "ts_ms": 32295130,
      "type": 6
    },
    {
      "channel_id": null,
      "detail_a": 16,
      "detail_b": 44514,
      "lifecycle_type": 0,
      "msg_type": null,
      "note": "",
      "packet_direction": 0,
      "packet_result": 0,
      "player_id": 2,
      "seq": 2389,
      "simulation_type": 0,
      "ts_ms": 32295180,
      "type": 6
    },
    {
      "channel_id": null,
      "detail_a": 0,
      "detail_b": 44521,
      "lifecycle_type": 0,
      "msg_type": null,
      "note": "",
      "packet_direction": 0,
      "packet_result": 0,
      "player_id": 0,
      "seq": 2406,
      "simulation_type": 0,
      "ts_ms": 32295296,
      "type": 6
    },
    {
      "channel_id": null,
      "detail_a": 0,
      "detail_b": 44575,
      "lifecycle_type": 0,
      "msg_type": null,
      "note": "",
      "packet_direction": 0,
      "packet_result": 0,
      "player_id": 2,
      "seq": 2450,
      "simulation_type": 0,
      "ts_ms": 32296196,
      "type": 6
    },
    {
      "channel_id": null,
      "detail_a": 0,
      "detail_b": 44580,
      "lifecycle_type": 0,
      "msg_type": null,
      "note": "",
      "packet_direction": 0,
      "packet_result": 0,
      "player_id": 1,
      "seq": 2462,
      "simulation_type": 1,
      "ts_ms": 32296280,
      "type": 6
    },
    {
      "channel_id": null,
      "detail_a": 0,
      "detail_b": 44588,
      "lifecycle_type": 0,
      "msg_type": null,
      "note": "",
      "packet_direction": 0,
      "packet_result": 0,
      "player_id": 0,
      "seq": 2473,
      "simulation_type": 0,
      "ts_ms": 32296413,
      "type": 6
    },
    {
      "channel_id": null,
      "detail_a": 0,
      "detail_b": 44605,
      "lifecycle_type": 0,
      "msg_type": null,
      "note": "",
      "packet_direction": 0,
      "packet_result": 0,
      "player_id": 1,
      "seq": 2487,
      "simulation_type": 0,
      "ts_ms": 32296696,
      "type": 6
    },
    {
      "channel_id": null,
      "detail_a": 4,
      "detail_b": 44639,
      "lifecycle_type": 0,
      "msg_type": null,
      "note": "",
      "packet_direction": 0,
      "packet_result": 0,
      "player_id": 2,
      "seq": 2514,
      "simulation_type": 0,
      "ts_ms": 32297263,
      "type": 6
    },
    {
      "channel_id": null,
      "detail_a": 0,
      "detail_b": 44646,
      "lifecycle_type": 0,
      "msg_type": null,
      "note": "",
      "packet_direction": 0,
      "packet_result": 0,
      "player_id": 1,
      "seq": 2528,
      "simulation_type": 1,
      "ts_ms": 32297380,
      "type": 6
    },
    {
      "channel_id": null,
      "detail_a": 0,
      "detail_b": 44651,
      "lifecycle_type": 0,
      "msg_type": null,
      "note": "",
      "packet_direction": 0,
      "packet_result": 0,
      "player_id": 0,
      "seq": 2536,
      "simulation_type": 0,
      "ts_ms": 32297463,
      "type": 6
    },
    {
      "channel_id": null,
      "detail_a": 0,
      "detail_b": 44665,
      "lifecycle_type": 0,
      "msg_type": null,
      "note": "",
      "packet_direction": 0,
      "packet_result": 0,
      "player_id": 1,
      "seq": 2547,
      "simulation_type": 0,
      "ts_ms": 32297697,
      "type": 6
    },
    {
      "channel_id": null,
      "detail_a": 2,
      "detail_b": 44703,
      "lifecycle_type": 0,
      "msg_type": null,
      "note": "",
      "packet_direction": 0,
      "packet_result": 0,
      "player_id": 2,
      "seq": 2578,
      "simulation_type": 0,
      "ts_ms": 32298329,
      "type": 6
    },
    {
      "channel_id": null,
      "detail_a": 0,
      "detail_b": 44709,
      "lifecycle_type": 0,
      "msg_type": null,
      "note": "",
      "packet_direction": 0,
      "packet_result": 0,
      "player_id": 1,
      "seq": 2591,
      "simulation_type": 1,
      "ts_ms": 32298430,
      "type": 6
    },
    {
      "channel_id": null,
      "detail_a": 0,
      "detail_b": 44716,
      "lifecycle_type": 0,
      "msg_type": null,
      "note": "",
      "packet_direction": 0,
      "packet_result": 0,
      "player_id": 0,
      "seq": 2601,
      "simulation_type": 0,
      "ts_ms": 32298546,
      "type": 6
    },
    {
      "channel_id": null,
      "detail_a": 0,
      "detail_b": 44727,
      "lifecycle_type": 0,
      "msg_type": null,
      "note": "",
      "packet_direction": 0,
      "packet_result": 0,
      "player_id": 1,
      "seq": 2609,
      "simulation_type": 0,
      "ts_ms": 32298730,
      "type": 6
    },
    {
      "channel_id": null,
      "detail_a": 1,
      "detail_b": 44763,
      "lifecycle_type": 0,
      "msg_type": null,
      "note": "",
      "packet_direction": 0,
      "packet_result": 0,
      "player_id": 2,
      "seq": 2638,
      "simulation_type": 0,
      "ts_ms": 32299330,
      "type": 6
    },
    {
      "channel_id": null,
      "detail_a": 0,
      "detail_b": 44778,
      "lifecycle_type": 0,
      "msg_type": null,
      "note": "",
      "packet_direction": 0,
      "packet_result": 0,
      "player_id": 0,
      "seq": 2663,
      "simulation_type": 0,
      "ts_ms": 32299580,
      "type": 6
    },
    {
      "channel_id": null,
      "detail_a": 0,
      "detail_b": 44778,
      "lifecycle_type": 0,
      "msg_type": null,
      "note": "",
      "packet_direction": 0,
      "packet_result": 0,
      "player_id": 1,
      "seq": 2660,
      "simulation_type": 1,
      "ts_ms": 32299580,
      "type": 6
    },
    {
      "channel_id": null,
      "detail_a": 0,
      "detail_b": 44803,
      "lifecycle_type": 0,
      "msg_type": null,
      "note": "",
      "packet_direction": 0,
      "packet_result": 0,
      "player_id": 1,
      "seq": 2685,
      "simulation_type": 0,
      "ts_ms": 32299996,
      "type": 6
    },
    {
      "channel_id": null,
      "detail_a": 0,
      "detail_b": 44824,
      "lifecycle_type": 0,
      "msg_type": null,
      "note": "",
      "packet_direction": 0,
      "packet_result": 0,
      "player_id": 2,
      "seq": 2699,
      "simulation_type": 0,
      "ts_ms": 32300347,
      "type": 6
    },
    {
      "channel_id": null,
      "detail_a": 0,
      "detail_b": 44841,
      "lifecycle_type": 0,
      "msg_type": null,
      "note": "",
      "packet_direction": 0,
      "packet_result": 0,
      "player_id": 0,
      "seq": 2726,
      "simulation_type": 0,
      "ts_ms": 32300630,
      "type": 6
    },
    {
      "channel_id": null,
      "detail_a": 0,
      "detail_b": 44846,
      "lifecycle_type": 0,
      "msg_type": null,
      "note": "",
      "packet_direction": 0,
      "packet_result": 0,
      "player_id": 1,
      "seq": 2728,
      "simulation_type": 1,
      "ts_ms": 32300713,
      "type": 6
    },
    {
      "channel_id": null,
      "detail_a": 0,
      "detail_b": 44866,
      "lifecycle_type": 0,
      "msg_type": null,
      "note": "",
      "packet_direction": 0,
      "packet_result": 0,
      "player_id": 1,
      "seq": 2748,
      "simulation_type": 0,
      "ts_ms": 32301046,
      "type": 6
    },
    {
      "channel_id": null,
      "detail_a": 4,
      "detail_b": 44885,
      "lifecycle_type": 0,
      "msg_type": null,
      "note": "",
      "packet_direction": 0,
      "packet_result": 0,
      "player_id": 2,
      "seq": 2760,
      "simulation_type": 0,
      "ts_ms": 32301363,
      "type": 6
    },
    {
      "channel_id": null,
      "detail_a": 0,
      "detail_b": 44909,
      "lifecycle_type": 0,
      "msg_type": null,
      "note": "",
      "packet_direction": 0,
      "packet_result": 0,
      "player_id": 0,
      "seq": 2794,
      "simulation_type": 0,
      "ts_ms": 32301764,
      "type": 6
    },
    {
      "channel_id": null,
      "detail_a": 0,
      "detail_b": 44919,
      "lifecycle_type": 0,
      "msg_type": null,
      "note": "",
      "packet_direction": 0,
      "packet_result": 0,
      "player_id": 1,
      "seq": 2801,
      "simulation_type": 1,
      "ts_ms": 32301929,
      "type": 6
    },
    {
      "channel_id": null,
      "detail_a": 0,
      "detail_b": 44926,
      "lifecycle_type": 0,
      "msg_type": null,
      "note": "",
      "packet_direction": 0,
      "packet_result": 0,
      "player_id": 1,
      "seq": 2808,
      "simulation_type": 0,
      "ts_ms": 32302046,
      "type": 6
    },
    {
      "channel_id": null,
      "detail_a": 4,
      "detail_b": 44948,
      "lifecycle_type": 0,
      "msg_type": null,
      "note": "",
      "packet_direction": 0,
      "packet_result": 0,
      "player_id": 2,
      "seq": 2823,
      "simulation_type": 0,
      "ts_ms": 32302413,
      "type": 6
    },
    {
      "channel_id": null,
      "detail_a": 0,
      "detail_b": 44970,
      "lifecycle_type": 0,
      "msg_type": null,
      "note": "",
      "packet_direction": 0,
      "packet_result": 0,
      "player_id": 0,
      "seq": 2855,
      "simulation_type": 0,
      "ts_ms": 32302779,
      "type": 6
    },
    {
      "channel_id": null,
      "detail_a": 0,
      "detail_b": 44988,
      "lifecycle_type": 0,
      "msg_type": null,
      "note": "",
      "packet_direction": 0,
      "packet_result": 0,
      "player_id": 1,
      "seq": 2870,
      "simulation_type": 1,
      "ts_ms": 32303080,
      "type": 6
    },
    {
      "channel_id": null,
      "detail_a": 4,
      "detail_b": 45008,
      "lifecycle_type": 0,
      "msg_type": null,
      "note": "",
      "packet_direction": 0,
      "packet_result": 0,
      "player_id": 2,
      "seq": 2883,
      "simulation_type": 0,
      "ts_ms": 32303413,
      "type": 6
    },
    {
      "channel_id": null,
      "detail_a": 0,
      "detail_b": 45017,
      "lifecycle_type": 0,
      "msg_type": null,
      "note": "",
      "packet_direction": 0,
      "packet_result": 0,
      "player_id": 1,
      "seq": 2899,
      "simulation_type": 0,
      "ts_ms": 32303563,
      "type": 6
    },
    {
      "channel_id": null,
      "detail_a": 0,
      "detail_b": 45048,
      "lifecycle_type": 0,
      "msg_type": null,
      "note": "",
      "packet_direction": 0,
      "packet_result": 0,
      "player_id": 0,
      "seq": 2933,
      "simulation_type": 0,
      "ts_ms": 32304079,
      "type": 6
    },
    {
      "channel_id": null,
      "detail_a": 0,
      "detail_b": 45063,
      "lifecycle_type": 0,
      "msg_type": null,
      "note": "",
      "packet_direction": 0,
      "packet_result": 0,
      "player_id": 1,
      "seq": 2945,
      "simulation_type": 1,
      "ts_ms": 32304330,
      "type": 6
    },
    {
      "channel_id": null,
      "detail_a": 4,
      "detail_b": 45073,
      "lifecycle_type": 0,
      "msg_type": null,
      "note": "",
      "packet_direction": 0,
      "packet_result": 0,
      "player_id": 2,
      "seq": 2948,
      "simulation_type": 0,
      "ts_ms": 32304496,
      "type": 6
    },
    {
      "channel_id": null,
      "detail_a": 0,
      "detail_b": 45096,
      "lifecycle_type": 0,
      "msg_type": null,
      "note": "",
      "packet_direction": 0,
      "packet_result": 0,
      "player_id": 1,
      "seq": 2978,
      "simulation_type": 0,
      "ts_ms": 32304880,
      "type": 6
    },
    {
      "channel_id": null,
      "detail_a": 0,
      "detail_b": 45121,
      "lifecycle_type": 0,
      "msg_type": null,
      "note": "",
      "packet_direction": 0,
      "packet_result": 0,
      "player_id": 0,
      "seq": 3006,
      "simulation_type": 0,
      "ts_ms": 32305297,
      "type": 6
    },
    {
      "channel_id": null,
      "detail_a": 1,
      "detail_b": 45134,
      "lifecycle_type": 0,
      "msg_type": null,
      "note": "",
      "packet_direction": 0,
      "packet_result": 0,
      "player_id": 2,
      "seq": 3009,
      "simulation_type": 0,
      "ts_ms": 32305514,
      "type": 6
    },
    {
      "channel_id": null,
      "detail_a": 0,
      "detail_b": 45139,
      "lifecycle_type": 0,
      "msg_type": null,
      "note": "",
      "packet_direction": 0,
      "packet_result": 0,
      "player_id": 1,
      "seq": 3021,
      "simulation_type": 1,
      "ts_ms": 32305597,
      "type": 6
    },
    {
      "channel_id": null,
      "detail_a": 0,
      "detail_b": 45160,
      "lifecycle_type": 0,
      "msg_type": null,
      "note": "",
      "packet_direction": 0,
      "packet_result": 0,
      "player_id": 1,
      "seq": 3042,
      "simulation_type": 0,
      "ts_ms": 32305947,
      "type": 6
    },
    {
      "channel_id": null,
      "detail_a": 0,
      "detail_b": 45187,
      "lifecycle_type": 0,
      "msg_type": null,
      "note": "",
      "packet_direction": 0,
      "packet_result": 0,
      "player_id": 0,
      "seq": 3072,
      "simulation_type": 0,
      "ts_ms": 32306396,
      "type": 6
    },
    {
      "channel_id": null,
      "detail_a": 8,
      "detail_b": 45198,
      "lifecycle_type": 0,
      "msg_type": null,
      "note": "",
      "packet_direction": 0,
      "packet_result": 0,
      "player_id": 2,
      "seq": 3073,
      "simulation_type": 0,
      "ts_ms": 32306578,
      "type": 6
    },
    {
      "channel_id": null,
      "detail_a": 0,
      "detail_b": 45226,
      "lifecycle_type": 0,
      "msg_type": null,
      "note": "",
      "packet_direction": 0,
      "packet_result": 0,
      "player_id": 1,
      "seq": 3108,
      "simulation_type": 1,
      "ts_ms": 32307046,
      "type": 6
    },
    {
      "channel_id": null,
      "detail_a": 0,
      "detail_b": 45254,
      "lifecycle_type": 0,
      "msg_type": null,
      "note": "",
      "packet_direction": 0,
      "packet_result": 0,
      "player_id": 0,
      "seq": 3139,
      "simulation_type": 0,
      "ts_ms": 32307513,
      "type": 6
    },
    {
      "channel_id": null,
      "detail_a": 1,
      "detail_b": 45259,
      "lifecycle_type": 0,
      "msg_type": null,
      "note": "",
      "packet_direction": 0,
      "packet_result": 0,
      "player_id": 2,
      "seq": 3134,
      "simulation_type": 0,
      "ts_ms": 32307597,
      "type": 6
    },
    {
      "channel_id": null,
      "detail_a": 0,
      "detail_b": 45270,
      "lifecycle_type": 0,
      "msg_type": null,
      "note": "",
      "packet_direction": 0,
      "packet_result": 0,
      "player_id": 1,
      "seq": 3152,
      "simulation_type": 0,
      "ts_ms": 32307779,
      "type": 6
    },
    {
      "channel_id": null,
      "detail_a": 0,
      "detail_b": 45290,
      "lifecycle_type": 0,
      "msg_type": null,
      "note": "",
      "packet_direction": 0,
      "packet_result": 0,
      "player_id": 1,
      "seq": 3172,
      "simulation_type": 1,
      "ts_ms": 32308113,
      "type": 6
    },
    {
      "channel_id": null,
      "detail_a": 0,
      "detail_b": 45326,
      "lifecycle_type": 0,
      "msg_type": null,
      "note": "",
      "packet_direction": 0,
      "packet_result": 0,
      "player_id": 0,
      "seq": 3211,
      "simulation_type": 0,
      "ts_ms": 32308713,
      "type": 6
    },
    {
      "channel_id": null,
      "detail_a": 0,
      "detail_b": 45326,
      "lifecycle_type": 0,
      "msg_type": null,
      "note": "",
      "packet_direction": 0,
      "packet_result": 0,
      "player_id": 2,
      "seq": 3201,
      "simulation_type": 0,
      "ts_ms": 32308713,
      "type": 6
    },
    {
      "channel_id": null,
      "detail_a": 0,
      "detail_b": 45349,
      "lifecycle_type": 0,
      "msg_type": null,
      "note": "",
      "packet_direction": 0,
      "packet_result": 0,
      "player_id": 1,
      "seq": 3231,
      "simulation_type": 0,
      "ts_ms": 32309096,
      "type": 6
    },
    {
      "channel_id": null,
      "detail_a": 0,
      "detail_b": 45351,
      "lifecycle_type": 0,
      "msg_type": null,
      "note": "",
      "packet_direction": 0,
      "packet_result": 0,
      "player_id": 1,
      "seq": 3233,
      "simulation_type": 1,
      "ts_ms": 32309129,
      "type": 6
    },
    {
      "channel_id": null,
      "detail_a": 0,
      "detail_b": 45388,
      "lifecycle_type": 0,
      "msg_type": null,
      "note": "",
      "packet_direction": 0,
      "packet_result": 0,
      "player_id": 2,
      "seq": 3263,
      "simulation_type": 0,
      "ts_ms": 32309746,
      "type": 6
    },
    {
      "channel_id": null,
      "detail_a": 0,
      "detail_b": 45391,
      "lifecycle_type": 0,
      "msg_type": null,
      "note": "",
      "packet_direction": 0,
      "packet_result": 0,
      "player_id": 0,
      "seq": 3276,
      "simulation_type": 0,
      "ts_ms": 32309796,
      "type": 6
    },
    {
      "channel_id": null,
      "detail_a": 0,
      "detail_b": 45412,
      "lifecycle_type": 0,
      "msg_type": null,
      "note": "",
      "packet_direction": 0,
      "packet_result": 0,
      "player_id": 1,
      "seq": 3294,
      "simulation_type": 1,
      "ts_ms": 32310146,
      "type": 6
    },
    {
      "channel_id": null,
      "detail_a": 0,
      "detail_b": 45431,
      "lifecycle_type": 0,
      "msg_type": null,
      "note": "",
      "packet_direction": 0,
      "packet_result": 0,
      "player_id": 1,
      "seq": 3313,
      "simulation_type": 0,
      "ts_ms": 32310463,
      "type": 6
    },
    {
      "channel_id": null,
      "detail_a": 0,
      "detail_b": 45448,
      "lifecycle_type": 0,
      "msg_type": null,
      "note": "",
      "packet_direction": 0,
      "packet_result": 0,
      "player_id": 2,
      "seq": 3323,
      "simulation_type": 0,
      "ts_ms": 32310746,
      "type": 6
    },
    {
      "channel_id": null,
      "detail_a": 0,
      "detail_b": 45456,
      "lifecycle_type": 0,
      "msg_type": null,
      "note": "",
      "packet_direction": 0,
      "packet_result": 0,
      "player_id": 0,
      "seq": 3341,
      "simulation_type": 0,
      "ts_ms": 32310879,
      "type": 6
    },
    {
      "channel_id": null,
      "detail_a": 0,
      "detail_b": 45480,
      "lifecycle_type": 0,
      "msg_type": null,
      "note": "",
      "packet_direction": 0,
      "packet_result": 0,
      "player_id": 1,
      "seq": 3362,
      "simulation_type": 1,
      "ts_ms": 32311279,
      "type": 6
    },
    {
      "channel_id": null,
      "detail_a": 0,
      "detail_b": 45509,
      "lifecycle_type": 0,
      "msg_type": null,
      "note": "",
      "packet_direction": 0,
      "packet_result": 0,
      "player_id": 2,
      "seq": 3384,
      "simulation_type": 0,
      "ts_ms": 32311763,
      "type": 6
    },
    {
      "channel_id": null,
      "detail_a": 0,
      "detail_b": 45517,
      "lifecycle_type": 0,
      "msg_type": null,
      "note": "",
      "packet_direction": 0,
      "packet_result": 0,
      "player_id": 0,
      "seq": 3402,
      "simulation_type": 0,
      "ts_ms": 32311896,
      "type": 6
    },
    {
      "channel_id": null,
      "detail_a": 8,
      "detail_b": 45529,
      "lifecycle_type": 0,
      "msg_type": null,
      "note": "",
      "packet_direction": 0,
      "packet_result": 0,
      "player_id": 1,
      "seq": 3411,
      "simulation_type": 0,
      "ts_ms": 32312097,
      "type": 6
    },
    {
      "channel_id": null,
      "detail_a": 0,
      "detail_b": 45542,
      "lifecycle_type": 0,
      "msg_type": null,
      "note": "",
      "packet_direction": 0,
      "packet_result": 0,
      "player_id": 1,
      "seq": 3424,
      "simulation_type": 1,
      "ts_ms": 32312313,
      "type": 6
    },
    {
      "channel_id": null,
      "detail_a": 0,
      "detail_b": 45569,
      "lifecycle_type": 0,
      "msg_type": null,
      "note": "",
      "packet_direction": 0,
      "packet_result": 0,
      "player_id": 2,
      "seq": 3444,
      "simulation_type": 0,
      "ts_ms": 32312763,
      "type": 6
    },
    {
      "channel_id": null,
      "detail_a": 0,
      "detail_b": 45581,
      "lifecycle_type": 0,
      "msg_type": null,
      "note": "",
      "packet_direction": 0,
      "packet_result": 0,
      "player_id": 0,
      "seq": 3466,
      "simulation_type": 0,
      "ts_ms": 32312963,
      "type": 6
    },
    {
      "channel_id": null,
      "detail_a": 1,
      "detail_b": 45596,
      "lifecycle_type": 0,
      "msg_type": null,
      "note": "",
      "packet_direction": 0,
      "packet_result": 0,
      "player_id": 1,
      "seq": 3478,
      "simulation_type": 0,
      "ts_ms": 32313213,
      "type": 6
    },
    {
      "channel_id": null,
      "detail_a": 0,
      "detail_b": 45604,
      "lifecycle_type": 0,
      "msg_type": null,
      "note": "",
      "packet_direction": 0,
      "packet_result": 0,
      "player_id": 1,
      "seq": 3486,
      "simulation_type": 1,
      "ts_ms": 32313346,
      "type": 6
    },
    {
      "channel_id": null,
      "detail_a": 0,
      "detail_b": 45637,
      "lifecycle_type": 0,
      "msg_type": null,
      "note": "",
      "packet_direction": 0,
      "packet_result": 0,
      "player_id": 2,
      "seq": 3512,
      "simulation_type": 0,
      "ts_ms": 32313897,
      "type": 6
    },
    {
      "channel_id": null,
      "detail_a": 0,
      "detail_b": 45646,
      "lifecycle_type": 0,
      "msg_type": null,
      "note": "",
      "packet_direction": 0,
      "packet_result": 0,
      "player_id": 0,
      "seq": 3531,
      "simulation_type": 0,
      "ts_ms": 32314047,
      "type": 6
    },
    {
      "channel_id": null,
      "detail_a": 0,
      "detail_b": 45664,
      "lifecycle_type": 0,
      "msg_type": null,
      "note": "",
      "packet_direction": 0,
      "packet_result": 0,
      "player_id": 1,
      "seq": 3546,
      "simulation_type": 1,
      "ts_ms": 32314346,
      "type": 6
    },
    {
      "channel_id": null,
      "detail_a": 0,
      "detail_b": 45701,
      "lifecycle_type": 0,
      "msg_type": null,
      "note": "",
      "packet_direction": 0,
      "packet_result": 0,
      "player_id": 2,
      "seq": 3576,
      "simulation_type": 0,
      "ts_ms": 32314963,
      "type": 6
    },
    {
      "channel_id": null,
      "detail_a": 0,
      "detail_b": 45708,
      "lifecycle_type": 0,
      "msg_type": null,
      "note": "",
      "packet_direction": 0,
      "packet_result": 0,
      "player_id": 0,
      "seq": 3593,
      "simulation_type": 0,
      "ts_ms": 32315080,
      "type": 6
    },
    {
      "channel_id": null,
      "detail_a": 0,
      "detail_b": 45761,
      "lifecycle_type": 0,
      "msg_type": null,
      "note": "",
      "packet_direction": 0,
      "packet_result": 0,
      "player_id": 2,
      "seq": 3636,
      "simulation_type": 0,
      "ts_ms": 32315963,
      "type": 6
    },
    {
      "channel_id": null,
      "detail_a": 0,
      "detail_b": 45769,
      "lifecycle_type": 0,
      "msg_type": null,
      "note": "",
      "packet_direction": 0,
      "packet_result": 0,
      "player_id": 0,
      "seq": 3654,
      "simulation_type": 0,
      "ts_ms": 32316096,
      "type": 6
    },
    {
      "channel_id": null,
      "detail_a": 0,
      "detail_b": 45821,
      "lifecycle_type": 0,
      "msg_type": null,
      "note": "",
      "packet_direction": 0,
      "packet_result": 0,
      "player_id": 2,
      "seq": 3696,
      "simulation_type": 0,
      "ts_ms": 32316963,
      "type": 6
    },
    {
      "channel_id": null,
      "detail_a": 0,
      "detail_b": 45831,
      "lifecycle_type": 0,
      "msg_type": null,
      "note": "",
      "packet_direction": 0,
      "packet_result": 0,
      "player_id": 0,
      "seq": 3716,
      "simulation_type": 0,
      "ts_ms": 32317129,
      "type": 6
    },
    {
      "channel_id": null,
      "detail_a": 4,
      "detail_b": 45882,
      "lifecycle_type": 0,
      "msg_type": null,
      "note": "",
      "packet_direction": 0,
      "packet_result": 0,
      "player_id": 2,
      "seq": 3757,
      "simulation_type": 0,
      "ts_ms": 32317980,
      "type": 6
    },
    {
      "channel_id": null,
      "detail_a": 0,
      "detail_b": 45899,
      "lifecycle_type": 0,
      "msg_type": null,
      "note": "",
      "packet_direction": 0,
      "packet_result": 0,
      "player_id": 0,
      "seq": 3784,
      "simulation_type": 0,
      "ts_ms": 32318263,
      "type": 6
    },
    {
      "channel_id": null,
      "detail_a": 8,
      "detail_b": 45943,
      "lifecycle_type": 0,
      "msg_type": null,
      "note": "",
      "packet_direction": 0,
      "packet_result": 0,
      "player_id": 2,
      "seq": 3818,
      "simulation_type": 0,
      "ts_ms": 32318996,
      "type": 6
    },
    {
      "channel_id": null,
      "detail_a": 0,
      "detail_b": 45974,
      "lifecycle_type": 0,
      "msg_type": null,
      "note": "",
      "packet_direction": 0,
      "packet_result": 0,
      "player_id": 0,
      "seq": 3859,
      "simulation_type": 0,
      "ts_ms": 32319513,
      "type": 6
    },
    {
      "channel_id": null,
      "detail_a": 4,
      "detail_b": 46003,
      "lifecycle_type": 0,
      "msg_type": null,
      "note": "",
      "packet_direction": 0,
      "packet_result": 0,
      "player_id": 2,
      "seq": 3878,
      "simulation_type": 0,
      "ts_ms": 32319997,
      "type": 6
    },
    {
      "channel_id": null,
      "detail_a": 0,
      "detail_b": 46044,
      "lifecycle_type": 0,
      "msg_type": null,
      "note": "",
      "packet_direction": 0,
      "packet_result": 0,
      "player_id": 0,
      "seq": 3929,
      "simulation_type": 0,
      "ts_ms": 32320680,
      "type": 6
    },
    {
      "channel_id": null,
      "detail_a": 4,
      "detail_b": 46069,
      "lifecycle_type": 0,
      "msg_type": null,
      "note": "",
      "packet_direction": 0,
      "packet_result": 0,
      "player_id": 2,
      "seq": 3944,
      "simulation_type": 0,
      "ts_ms": 32321096,
      "type": 6
    },
    {
      "channel_id": null,
      "detail_a": 0,
      "detail_b": 46109,
      "lifecycle_type": 0,
      "msg_type": null,
      "note": "",
      "packet_direction": 0,
      "packet_result": 0,
      "player_id": 0,
      "seq": 3994,
      "simulation_type": 0,
      "ts_ms": 32321763,
      "type": 6
    },
    {
      "channel_id": null,
      "detail_a": 8,
      "detail_b": 46132,
      "lifecycle_type": 0,
      "msg_type": null,
      "note": "",
      "packet_direction": 0,
      "packet_result": 0,
      "player_id": 2,
      "seq": 4007,
      "simulation_type": 0,
      "ts_ms": 32322147,
      "type": 6
    },
    {
      "channel_id": null,
      "detail_a": 0,
      "detail_b": 46181,
      "lifecycle_type": 0,
      "msg_type": null,
      "note": "",
      "packet_direction": 0,
      "packet_result": 0,
      "player_id": 0,
      "seq": 4066,
      "simulation_type": 0,
      "ts_ms": 32322963,
      "type": 6
    },
    {
      "channel_id": null,
      "detail_a": 4,
      "detail_b": 46195,
      "lifecycle_type": 0,
      "msg_type": null,
      "note": "",
      "packet_direction": 0,
      "packet_result": 0,
      "player_id": 2,
      "seq": 4070,
      "simulation_type": 0,
      "ts_ms": 32323196,
      "type": 6
    },
    {
      "channel_id": null,
      "detail_a": 0,
      "detail_b": 46258,
      "lifecycle_type": 0,
      "msg_type": null,
      "note": "",
      "packet_direction": 0,
      "packet_result": 0,
      "player_id": 2,
      "seq": 4133,
      "simulation_type": 0,
      "ts_ms": 32324246,
      "type": 6
    },
    {
      "channel_id": null,
      "detail_a": 0,
      "detail_b": 46270,
      "lifecycle_type": 0,
      "msg_type": null,
      "note": "",
      "packet_direction": 0,
      "packet_result": 0,
      "player_id": 0,
      "seq": 4155,
      "simulation_type": 0,
      "ts_ms": 32324446,
      "type": 6
    },
    {
      "channel_id": null,
      "detail_a": 8,
      "detail_b": 46325,
      "lifecycle_type": 0,
      "msg_type": null,
      "note": "",
      "packet_direction": 0,
      "packet_result": 0,
      "player_id": 2,
      "seq": 4200,
      "simulation_type": 0,
      "ts_ms": 32325363,
      "type": 6
    },
    {
      "channel_id": null,
      "detail_a": 0,
      "detail_b": 46332,
      "lifecycle_type": 0,
      "msg_type": null,
      "note": "",
      "packet_direction": 0,
      "packet_result": 0,
      "player_id": 0,
      "seq": 4217,
      "simulation_type": 0,
      "ts_ms": 32325480,
      "type": 6
    },
    {
      "channel_id": null,
      "detail_a": 0,
      "detail_b": 46386,
      "lifecycle_type": 0,
      "msg_type": null,
      "note": "",
      "packet_direction": 0,
      "packet_result": 0,
      "player_id": 2,
      "seq": 4261,
      "simulation_type": 0,
      "ts_ms": 32326380,
      "type": 6
    },
    {
      "channel_id": null,
      "detail_a": 0,
      "detail_b": 46400,
      "lifecycle_type": 0,
      "msg_type": null,
      "note": "",
      "packet_direction": 0,
      "packet_result": 0,
      "player_id": 0,
      "seq": 4285,
      "simulation_type": 0,
      "ts_ms": 32326613,
      "type": 6
    },
    {
      "channel_id": null,
      "detail_a": 0,
      "detail_b": 46449,
      "lifecycle_type": 0,
      "msg_type": null,
      "note": "",
      "packet_direction": 0,
      "packet_result": 0,
      "player_id": 2,
      "seq": 4324,
      "simulation_type": 0,
      "ts_ms": 32327430,
      "type": 6
    },
    {
      "channel_id": null,
      "detail_a": 4,
      "detail_b": 46510,
      "lifecycle_type": 0,
      "msg_type": null,
      "note": "",
      "packet_direction": 0,
      "packet_result": 0,
      "player_id": 2,
      "seq": 4385,
      "simulation_type": 0,
      "ts_ms": 32328446,
      "type": 6
    },
    {
      "channel_id": null,
      "detail_a": 0,
      "detail_b": 46516,
      "lifecycle_type": 0,
      "msg_type": null,
      "note": "",
      "packet_direction": 0,
      "packet_result": 0,
      "player_id": 0,
      "seq": 4401,
      "simulation_type": 0,
      "ts_ms": 32328546,
      "type": 6
    },
    {
      "channel_id": null,
      "detail_a": 4,
      "detail_b": 46570,
      "lifecycle_type": 0,
      "msg_type": null,
      "note": "",
      "packet_direction": 0,
      "packet_result": 0,
      "player_id": 2,
      "seq": 4445,
      "simulation_type": 0,
      "ts_ms": 32329447,
      "type": 6
    },
    {
      "channel_id": null,
      "detail_a": 0,
      "detail_b": 46578,
      "lifecycle_type": 0,
      "msg_type": null,
      "note": "",
      "packet_direction": 0,
      "packet_result": 0,
      "player_id": 0,
      "seq": 4463,
      "simulation_type": 0,
      "ts_ms": 32329579,
      "type": 6
    },
    {
      "channel_id": null,
      "detail_a": 0,
      "detail_b": 46631,
      "lifecycle_type": 0,
      "msg_type": null,
      "note": "",
      "packet_direction": 0,
      "packet_result": 0,
      "player_id": 2,
      "seq": 4506,
      "simulation_type": 0,
      "ts_ms": 32330462,
      "type": 6
    },
    {
      "channel_id": null,
      "detail_a": 0,
      "detail_b": 46640,
      "lifecycle_type": 0,
      "msg_type": null,
      "note": "",
      "packet_direction": 0,
      "packet_result": 0,
      "player_id": 0,
      "seq": 4525,
      "simulation_type": 0,
      "ts_ms": 32330613,
      "type": 6
    },
    {
      "channel_id": null,
      "detail_a": 6,
      "detail_b": 46689,
      "lifecycle_type": 0,
      "msg_type": null,
      "note": "server flow: end_of_match",
      "packet_direction": 0,
      "packet_result": 0,
      "player_id": null,
      "seq": 0,
      "simulation_type": 0,
      "ts_ms": 32331430,
      "type": 7
    },
    {
      "channel_id": null,
      "detail_a": 1,
      "detail_b": 46689,
      "lifecycle_type": 0,
      "msg_type": null,
      "note": "",
      "packet_direction": 0,
      "packet_result": 0,
      "player_id": null,
      "seq": 0,
      "simulation_type": 2,
      "ts_ms": 32331430,
      "type": 6
    },
    {
      "channel_id": null,
      "detail_a": 0,
      "detail_b": 46869,
      "lifecycle_type": 0,
      "msg_type": null,
      "note": "server flow: lobby",
      "packet_direction": 0,
      "packet_result": 0,
      "player_id": null,
      "seq": 0,
      "simulation_type": 0,
      "ts_ms": 32334429,
      "type": 7
    },
    {
      "channel_id": null,
      "detail_a": 0,
      "detail_b": 0,
      "lifecycle_type": 3,
      "msg_type": null,
      "note": "",
      "packet_direction": 0,
      "packet_result": 0,
      "player_id": 0,
      "seq": 0,
      "simulation_type": 0,
      "ts_ms": 32336041,
      "type": 3
    },
    {
      "channel_id": null,
      "detail_a": 1,
      "detail_b": 0,
      "lifecycle_type": 3,
      "msg_type": null,
      "note": "",
      "packet_direction": 0,
      "packet_result": 0,
      "player_id": 1,
      "seq": 0,
      "simulation_type": 0,
      "ts_ms": 32337576,
      "type": 3
    },
    {
      "channel_id": null,
      "detail_a": 0,
      "detail_b": 47253,
      "lifecycle_type": 0,
      "msg_type": null,
      "note": "server idle",
      "packet_direction": 0,
      "packet_result": 0,
      "player_id": null,
      "seq": 0,
      "simulation_type": 0,
      "ts_ms": 32340834,
      "type": 7
    },
    {
      "channel_id": null,
      "detail_a": 2,
      "detail_b": 0,
      "lifecycle_type": 3,
      "msg_type": null,
      "note": "",
      "packet_direction": 0,
      "packet_result": 0,
      "player_id": 2,
      "seq": 0,
      "simulation_type": 0,
      "ts_ms": 32340834,
      "type": 3
    },
    {
      "channel_id": null,
      "detail_a": 0,
      "detail_b": 0,
      "lifecycle_type": 0,
      "msg_type": null,
      "note": "session ended",
      "packet_direction": 0,
      "packet_result": 0,
      "player_id": null,
      "seq": 0,
      "simulation_type": 0,
      "ts_ms": 32349459,
      "type": 2
    }
  ],
  "report": "net_diagnostics_report",
  "report_version": 1,
  "server_flow": {
    "idle": true,
    "state": "lobby"
  },
  "session": {
    "active": false,
    "begin_ms": 31553278,
    "duration_ms": 796181,
    "end_ms": 32349459,
    "recent_events_evicted": 904,
    "recent_events_recorded": 1160,
    "ticks": 47770
  },
  "session_owner": "server",
  "simulation_continuity": {
    "bombs_placed": 44,
    "bricks_destroyed": 41,
    "buffered_deadline_recoveries": 1943,
    "direct_deadline_consumes": 45140,
    "round_wins_by_player_id": [
      2,
      1,
      0,
      0
    ],
    "rounds_drawn": 2,
    "rounds_ended": 5,
    "simulation_gaps": 11204
  },
  "transport_samples": [
    {
      "loss_permille": 0,
      "player_id": 0,
      "q_rel": 0,
      "q_unrel": 0,
      "rtt_ms": 7,
      "rtt_var_ms": 4,
      "ts_ms": 32334280
    },
    {
      "loss_permille": 0,
      "player_id": 1,
      "q_rel": 0,
      "q_unrel": 0,
      "rtt_ms": 64,
      "rtt_var_ms": 10,
      "ts_ms": 32334280
    },
    {
      "loss_permille": 2,
      "player_id": 2,
      "q_rel": 0,
      "q_unrel": 0,
      "rtt_ms": 181,
      "rtt_var_ms": 8,
      "ts_ms": 32334280
    }
  ]
}
